torch_trainer/__init__.py
torch_trainer/callbacks.py
torch_trainer/trainer.py
torch_trainer-0.1.dist-info/DESCRIPTION.rst
torch_trainer-0.1.dist-info/METADATA
torch_trainer-0.1.dist-info/RECORD
torch_trainer-0.1.dist-info/WHEEL
torch_trainer-0.1.dist-info/metadata.json
torch_trainer-0.1.dist-info/top_level.txt
