Metadata-Version: 2.0
Name: torch-trainer
Version: 0.1
Summary: Bare bones PyTorch training utility
Home-page: http://github.com/cemoody/torch_trainer
Author: Christopher Erick Moody
Author-email: chrisemoody@gmail.com
License: MIT
Platform: UNKNOWN
